bird_devexpress/__init__.py
bird_devexpress/ui/DevExpress.BonusSkins.v22.2.dll
bird_devexpress/ui/DevExpress.Utils.v22.2.dll
bird_devexpress/ui/DevExpress.XtraBars.v22.2.dll
bird_devexpress/ui/DevExpress.XtraEditors.v22.2.dll
bird_devexpress/ui/DevExpress.XtraRichEdit.v22.2.dll
bird_devexpress/ui/__init__.py
bird_devexpress/ui/button.py
bird_devexpress/ui/fluentwindow.py
bird_devexpress/ui/panel.py
bird_devexpress/ui/richedit.py
bird_devexpress/ui/settings.py
bird_devexpress/ui/setup.py
bird_devexpress/ui/style.py
bird_devexpress/ui/tab.py
bird_devexpress/ui/taskbar_assistant.py
bird_devexpress/ui/toggle.py
bird_devexpress/ui/widget.py
bird_devexpress/ui/window.py
bird_dev_form_devexpress-1.0.0a3.dist-info/METADATA
bird_dev_form_devexpress-1.0.0a3.dist-info/WHEEL
bird_dev_form_devexpress-1.0.0a3.dist-info/top_level.txt
bird_dev_form_devexpress-1.0.0a3.dist-info/RECORD
